shrecc/__init__.py
shrecc/database.py
shrecc/download.py
shrecc/treatment.py
shrecc/data/el_map_all_norm.csv
shrecc/data/generation_units_by_country.csv
shrecc/data/techs_agg.json
shrecc-0.0.4.dist-info/licenses/LICENSE
shrecc-0.0.4.dist-info/METADATA
shrecc-0.0.4.dist-info/WHEEL
shrecc-0.0.4.dist-info/top_level.txt
shrecc-0.0.4.dist-info/RECORD
