Metadata-Version: 2.4
Name: shrecc
Version: 0.0.4
Summary: SHRECC: Smooth Hourly Resolution Electricity Consumption Calculation
Author-email: Sabina Bednářová <sabina.bednarova@list.lu>
Maintainer-email: Sabina Bednářová <sabina.bednarova@list.lu>
License-Expression: MIT
Project-URL: source, https://git.list.lu/shrecc_project/SHRECC
Project-URL: homepage, https://git.list.lu/shrecc_project/SHRECC
Project-URL: tracker, https://git.list.lu/shrecc_project/SHRECC/issues
Classifier: Development Status :: 4 - Beta
Classifier: Programming Language :: Python
Classifier: Programming Language :: Python :: 3
Classifier: Programming Language :: Python :: 3.10
Classifier: Programming Language :: Python :: 3.11
Classifier: Programming Language :: Python :: 3.12
Classifier: Programming Language :: Python :: 3.13
Classifier: Natural Language :: English
Classifier: Operating System :: OS Independent
Classifier: Topic :: Scientific/Engineering
Requires-Python: >=3.10
License-File: LICENSE
Requires-Dist: bw2data>=4.4.2
Requires-Dist: pypardiso
Requires-Dist: pandas<3,>=2
Requires-Dist: numpy<3
Requires-Dist: numpy>2; python_version >= "3.13"
Requires-Dist: requests>=2.32
Requires-Dist: fs
Requires-Dist: scipy>=1.14
Requires-Dist: appdirs
Provides-Extra: testing
Requires-Dist: shrecc; extra == "testing"
Requires-Dist: pytest; extra == "testing"
Requires-Dist: pytest-cov; extra == "testing"
Requires-Dist: python-coveralls; extra == "testing"
Provides-Extra: dev
Requires-Dist: build; extra == "dev"
Requires-Dist: pre-commit; extra == "dev"
Requires-Dist: pylint; extra == "dev"
Requires-Dist: pytest; extra == "dev"
Requires-Dist: pytest-cov; extra == "dev"
Requires-Dist: pytest-randomly; extra == "dev"
Requires-Dist: setuptools; extra == "dev"
Requires-Dist: ruff>=0.11.12; extra == "dev"
Requires-Dist: black>=25.1.0; extra == "dev"
Provides-Extra: docs
Requires-Dist: furo==2024.1.29; extra == "docs"
Requires-Dist: myst_parser==2.0.0; extra == "docs"
Requires-Dist: sphinx==7.2.6; extra == "docs"
Requires-Dist: sphinx-autobuild>=2024.10.3; extra == "docs"
Requires-Dist: ipython>=8.37.0; extra == "docs"
Requires-Dist: sphinx-rtd-theme>=3.0.2; extra == "docs"
Requires-Dist: myst-parser>=2.0.0; extra == "docs"
Requires-Dist: sphinx-design>=0.6.1; extra == "docs"
Requires-Dist: sphinx-copybutton>=0.5.2; extra == "docs"
Requires-Dist: sphinx-autoapi>=3.5.0; extra == "docs"
Requires-Dist: sphinx-notfound-page>=1.1.0; extra == "docs"
Requires-Dist: myst-nb>=1.2.0; extra == "docs"
Dynamic: license-file
